[
    {  
        "id":1,
              "title": "PTS"
      },
      {  
        "id":2,
              "title": "PJ"
      },
      {  
        "id":3,
              "title": "G"
      },
      {  
        "id":4,
              "title": "E"
      },
      {  
        "id":5,
              "title": "P"
      },
      {  
        "id":6,
              "title": "GF"
      },
      {  
        "id":7,
              "title": "GC"
      },
      {  
        "id":8,
              "title": "DG"
      }
  ]